[
    { "position":1, "number":2, "class":450 },
    { "position":2, "number":94, "class":450 },
    { "position":3, "number":4, "class":450 },
    { "position":4, "number":27, "class":450 },
    { "position":5, "number":32, "class":450 },
    { "position":6, "number":21, "class":450 },
    { "position":7, "number":51, "class":450 },
    { "position":8, "number":14, "class":450 },
    { "position":9, "number":7, "class":450 },
    { "position":10, "number":46, "class":450 },
    { "position":11, "number":45, "class":450 },
    { "position":12, "number":12, "class":450 },
    { "position":13, "number":17, "class":450 },
    { "position":14, "number":49, "class":450 },
    { "position":15, "number":77, "class":450 },
    { "position":16, "number":86, "class":450 },
    { "position":17, "number":11, "class":450 },
    { "position":18, "number":146, "class":450 },
    { "position":19, "number":43, "class":450 },
    { "position":20, "number":72, "class":450 },
    { "position":21, "number":122, "class":450 },
    { "position":22, "number":57, "class":450 },
    { "position":1, "number":47, "class":250 },
    { "position":2, "number":31, "class":250 },
    { "position":3, "number":24, "class":250 },
    { "position":4, "number":16, "class":250 },
    { "position":5, "number":41, "class":250 },
    { "position":6, "number":10, "class":250 },
    { "position":7, "number":83, "class":250 },
    { "position":8, "number":60, "class":250 },
    { "position":9, "number":92, "class":250 },
    { "position":10, "number":55, "class":250 },
    { "position":11, "number":59, "class":250 },
    { "position":12, "number":87, "class":250 },
    { "position":13, "number":89, "class":250 },
    { "position":14, "number":75, "class":250 },
    { "position":15, "number":192, "class":250 },
    { "position":16, "number":74, "class":250 },
    { "position":17, "number":56, "class":250 },
    { "position":18, "number":62, "class":250 },
    { "position":19, "number":73, "class":250 },
    { "position":20, "number":137, "class":250 },
    { "position":21, "number":682, "class":250 },
    { "position":22, "number":50, "class":250 }
]